{"EntityKeyName":"int","EntityDisplayName":"友情链接分类","BaseClassName":"AuditedEntity","BaseClassDtoName":"AuditedEntityDto","BaseClassNameList":"","Name":"BlogrollType","LowerName":"blogrollType","ParentDirName":"Blogrolls","ParentDirLowerName":"blogrolls","SplitName":"blogroll-type","NameSplit":["blogroll","type"],"Namespace":"LTMCompanyName.YoyoCmsTemplate.Modules.WebSiteSetting.Blogrolls","Properties":[{"Checked":true,"EditChecked":true,"ListChecked":true,"FieldName":"Name","FieldDisplayName":"分类名称","Required":true,"MinLength":null,"MaxLength":64,"RegularExpression":null,"FieldTypeStr":"string","FieldTypeStrFirstCharToLower":"string","FieldType":null,"CtrlTypes":["Text","bool","Checkbox","Textarea","DatePicker","DateTimePicker","TimePicker","DropdownList","Enums","Radio","double","float","int","long"],"CtrlTypeIndex":0,"IsCollection":false,"FieldNameFirstLower":"name","ContrlType":"Text","AttributesList":["[MaxLength(100)]"],"IsSimpleProperty":true,"IsRelation":false,"RelatedEntityName":null}]}