{"EntityKeyName":"Guid","EntityDisplayName":"人员","BaseClassName":"FullAuditedEntity<Guid>","BaseClassDtoName":"FullAuditedEntityDto<Guid>","BaseClassNameList":"","Name":"Person","LowerName":"person","ParentDirName":"Persons","ParentDirLowerName":"persons","SplitName":"person","NameSplit":["person"],"Namespace":"LTMCompanyName.YoyoCmsTemplate.PhoneBooks.Persons","Properties":[{"Checked":true,"EditChecked":true,"ListChecked":true,"FieldName":"Name","FieldDisplayName":"名称","Required":true,"MinLength":null,"MaxLength":64,"RegularExpression":null,"FieldTypeStr":"string","FieldTypeStrFirstCharToLower":"string","FieldType":null,"CtrlTypes":["Text","bool","Checkbox","Textarea","DatePicker","DateTimePicker","TimePicker","DropdownList","Enums","Radio","double","float","int","long"],"CtrlTypeIndex":0,"IsCollection":false,"FieldNameFirstLower":"name","ContrlType":"Text","AttributesList":["[Required]","[MaxLength(AppConsts.MaxNameLength)]"],"IsSimpleProperty":true,"IsRelation":false,"RelatedEntityName":null},{"Checked":true,"EditChecked":true,"ListChecked":true,"FieldName":"EmailAddress","FieldDisplayName":"邮箱地址","Required":false,"MinLength":null,"MaxLength":64,"RegularExpression":null,"FieldTypeStr":"string","FieldTypeStrFirstCharToLower":"string","FieldType":null,"CtrlTypes":["Text","bool","Checkbox","Textarea","DatePicker","DateTimePicker","TimePicker","DropdownList","Enums","Radio","double","float","int","long"],"CtrlTypeIndex":0,"IsCollection":false,"FieldNameFirstLower":"emailAddress","ContrlType":"Text","AttributesList":["[MaxLength(AppConsts.MaxEmailAddressLength)]"],"IsSimpleProperty":true,"IsRelation":false,"RelatedEntityName":null},{"Checked":true,"EditChecked":true,"ListChecked":true,"FieldName":"Address","FieldDisplayName":"地址","Required":false,"MinLength":null,"MaxLength":64,"RegularExpression":null,"FieldTypeStr":"string","FieldTypeStrFirstCharToLower":"string","FieldType":null,"CtrlTypes":["Text","bool","Checkbox","Textarea","DatePicker","DateTimePicker","TimePicker","DropdownList","Enums","Radio","double","float","int","long"],"CtrlTypeIndex":0,"IsCollection":false,"FieldNameFirstLower":"address","ContrlType":"Text","AttributesList":["[MaxLength(AppConsts.MaxAddressLength)]"],"IsSimpleProperty":true,"IsRelation":false,"RelatedEntityName":null}]}